{"_ts":[1509519687],"_r":{"breakdown":{"html":{"bytes":[96108],"requests":[37]},"js":{"bytes":[893128],"requests":[51]},"css":{"bytes":[32265],"requests":[2]},"image":{"bytes":[153570],"requests":[50]},"flash":{"bytes":[0],"requests":[0]},"font":{"bytes":[5531],"requests":[1]},"video":{"bytes":[0],"requests":[0]},"other":{"bytes":[2323],"requests":[19]}},"date":[1509519687],"domElements":[798],"domInteractive":[1621],"firstPaint":[1468],"fullyLoaded":[9245],"id":["171101_4G_f16c37850287745b9019d4ceb9b17ef2"],"loadTime":[5281],"render":[1467],"SpeedIndex":[1902],"TTFB":[1026],"videoFrames":[[{"_i":"ms_000000.jpg","_t":0,"_vc":0},{"_i":"ms_001467.jpg","_t":1467,"_vc":63},{"_i":"ms_001567.jpg","_t":1567,"_vc":69},{"_i":"ms_002033.jpg","_t":2033,"_vc":69},{"_i":"ms_002067.jpg","_t":2067,"_vc":69},{"_i":"ms_002133.jpg","_t":2133,"_vc":92},{"_i":"ms_002167.jpg","_t":2167,"_vc":92},{"_i":"ms_002200.jpg","_t":2200,"_vc":92},{"_i":"ms_002233.jpg","_t":2233,"_vc":92},{"_i":"ms_002267.jpg","_t":2267,"_vc":92},{"_i":"ms_002300.jpg","_t":2300,"_vc":92},{"_i":"ms_002333.jpg","_t":2333,"_vc":92},{"_i":"ms_002433.jpg","_t":2433,"_vc":92},{"_i":"ms_002467.jpg","_t":2467,"_vc":92},{"_i":"ms_003067.jpg","_t":3067,"_vc":92},{"_i":"ms_003200.jpg","_t":3200,"_vc":92},{"_i":"ms_003267.jpg","_t":3267,"_vc":92},{"_i":"ms_003500.jpg","_t":3500,"_vc":92},{"_i":"ms_003533.jpg","_t":3533,"_vc":93},{"_i":"ms_003567.jpg","_t":3567,"_vc":93},{"_i":"ms_004000.jpg","_t":4000,"_vc":93},{"_i":"ms_004100.jpg","_t":4100,"_vc":93},{"_i":"ms_004533.jpg","_t":4533,"_vc":93},{"_i":"ms_004800.jpg","_t":4800,"_vc":93},{"_i":"ms_004867.jpg","_t":4867,"_vc":99},{"_i":"ms_005300.jpg","_t":5300,"_vc":99},{"_i":"ms_005567.jpg","_t":5567,"_vc":99},{"_i":"ms_005800.jpg","_t":5800,"_vc":99},{"_i":"ms_006567.jpg","_t":6567,"_vc":99},{"_i":"ms_006600.jpg","_t":6600,"_vc":100},{"_i":"ms_006667.jpg","_t":6667,"_vc":100},{"_i":"ms_006700.jpg","_t":6700,"_vc":100},{"_i":"ms_006733.jpg","_t":6733,"_vc":100}]],"visualComplete":[6600],"lighthouse":[36],"pagespeed":[80]}}