{"_ts":[1561948420],"_r":{"breakdown":{"html":{"bytes":[88258],"requests":[45]},"js":{"bytes":[762720],"requests":[27]},"css":{"bytes":[12995],"requests":[3]},"image":{"bytes":[21570],"requests":[47]},"flash":{"bytes":[0],"requests":[0]},"font":{"bytes":[8748],"requests":[1]},"video":{"bytes":[0],"requests":[0]},"other":{"bytes":[1631],"requests":[12]}},"date":[1561948420],"domElements":[662],"domInteractive":[1429],"firstPaint":[1054.7699999952],"fullyLoaded":[4665],"id":["190701_40_5bbc9102c732b486d1fd0aec3927df52"],"loadTime":[3014],"render":[1100],"SpeedIndex":[1410],"TTFB":[727],"videoFrames":[[{"_i":"ms_000000.jpg","_t":0,"_vc":0},{"_i":"ms_001100.jpg","_t":1100,"_vc":52},{"_i":"ms_001200.jpg","_t":1200,"_vc":57},{"_i":"ms_001300.jpg","_t":1300,"_vc":57},{"_i":"ms_001400.jpg","_t":1400,"_vc":57},{"_i":"ms_001500.jpg","_t":1500,"_vc":57},{"_i":"ms_001800.jpg","_t":1800,"_vc":100},{"_i":"ms_002000.jpg","_t":2000,"_vc":99},{"_i":"ms_002400.jpg","_t":2400,"_vc":100}]],"visualComplete":[1800],"lighthouse":[35],"pagespeed":[80]}}