{"_ts":[1577979578],"_r":{"breakdown":{"html":{"bytes":[95572],"requests":[84]},"js":{"bytes":[855855],"requests":[30]},"css":{"bytes":[13930],"requests":[3]},"image":{"bytes":[133867],"requests":[57]},"flash":{"bytes":[0],"requests":[0]},"font":{"bytes":[13896],"requests":[2]},"video":{"bytes":[0],"requests":[0]},"other":{"bytes":[11390],"requests":[13]}},"date":[1577979578],"domElements":[674],"domInteractive":[2181],"firstPaint":[1235.3250000015],"fullyLoaded":[6348],"id":["200102_PF_8faf26d9c1b4bcc3f3b6c6934642fcd7"],"loadTime":[3790],"render":[1200],"SpeedIndex":[1791],"TTFB":[857],"videoFrames":[[{"_i":"ms_000000.jpg","_t":0,"_vc":0},{"_i":"ms_001200.jpg","_t":1200,"_vc":58},{"_i":"ms_001300.jpg","_t":1300,"_vc":58},{"_i":"ms_001700.jpg","_t":1700,"_vc":58},{"_i":"ms_001800.jpg","_t":1800,"_vc":58},{"_i":"ms_001900.jpg","_t":1900,"_vc":58},{"_i":"ms_002000.jpg","_t":2000,"_vc":58},{"_i":"ms_002600.jpg","_t":2600,"_vc":99},{"_i":"ms_002700.jpg","_t":2700,"_vc":99},{"_i":"ms_002900.jpg","_t":2900,"_vc":100}]],"visualComplete":[2900],"lighthouse":[35],"pagespeed":[76]}}